cloack/__init__.py
cloack/constants.py
cloack-0.1.0.dist-info/LICENSE
cloack-0.1.0.dist-info/WHEEL
cloack-0.1.0.dist-info/METADATA
cloack-0.1.0.dist-info/RECORD
