Metadata-Version: 2.1
Name: cloack
Version: 0.1.0
Summary: A Python package to truncate dates and times.
Home-page: https://github.com/joaopalmeiro/cloack
License: MIT
Author: João Palmeiro
Author-email: jm.palmeiro@campus.fct.unl.pt
Requires-Python: >=3.7,<4.0
Classifier: Development Status :: 4 - Beta
Classifier: Intended Audience :: Developers
Classifier: Intended Audience :: Science/Research
Classifier: License :: OSI Approved :: MIT License
Classifier: Operating System :: OS Independent
Classifier: Programming Language :: Python :: 3
Classifier: Programming Language :: Python :: 3.7
Classifier: Programming Language :: Python :: 3.8
Classifier: Programming Language :: Python :: 3.9
Classifier: Programming Language :: Python :: 3.10
Classifier: Programming Language :: Python :: 3.11
Classifier: Topic :: Software Development :: Libraries :: Python Modules
Project-URL: Bug Tracker, https://github.com/joaopalmeiro/cloack/issues
Project-URL: Changelog, https://github.com/joaopalmeiro/cloack/blob/main/CHANGELOG.md
Project-URL: Repository, https://github.com/joaopalmeiro/cloack
